smvplot/__init__.py
smvplot/visualize.py
smvplot-0.0.3.1.dist-info/LICENSE
smvplot-0.0.3.1.dist-info/METADATA
smvplot-0.0.3.1.dist-info/WHEEL
smvplot-0.0.3.1.dist-info/entry_points.txt
smvplot-0.0.3.1.dist-info/top_level.txt
smvplot-0.0.3.1.dist-info/RECORD
