Metadata-Version: 2.1
Name: smvplot
Version: 0.0.3.1
Summary: smvplot is a cmd line python tool to generate IGV-like screenshots
Home-page: https://github.com/NagaComBio/smvplot
Author: Nagarajan Paramasivam
Author-email: n.paramasivam@dkfz.de
Project-URL: Bug Tracker, https://github.com/NagaComBio/smvplot/issues
Classifier: Programming Language :: Python :: 3
Classifier: License :: OSI Approved :: MIT License
Classifier: Operating System :: OS Independent
Requires-Python: >=3.6
License-File: LICENSE
Requires-Dist: matplotlib
Provides-Extra: pysam
Requires-Dist: pysam ; extra == 'pysam'
Provides-Extra: pysamstats
Requires-Dist: pysamstats ; extra == 'pysamstats'
